MANIFEST.in
README.rst
setup.py
demo/__init__.py
demo/app.py
demo/fabfile.py
demo/manage.py
demo/settings.py
demo/urls.py
feedzilla/__init__.py
feedzilla/admin.py
feedzilla/context_processor.py
feedzilla/filter.py
feedzilla/forms.py
feedzilla/models.py
feedzilla/settings.py
feedzilla/signals.py
feedzilla/syndication.py
feedzilla/tests.py
feedzilla/urls.py
feedzilla/views.py
feedzilla.egg-info/PKG-INFO
feedzilla.egg-info/SOURCES.txt
feedzilla.egg-info/dependency_links.txt
feedzilla.egg-info/top_level.txt
feedzilla/locale/pt_BR/LC_MESSAGES/django.mo
feedzilla/locale/pt_BR/LC_MESSAGES/django.po
feedzilla/locale/ru/LC_MESSAGES/django.mo
feedzilla/locale/ru/LC_MESSAGES/django.po
feedzilla/locale/tr/LC_MESSAGES/django.po
feedzilla/management/__init__.py
feedzilla/management/commands/__init__.py
feedzilla/management/commands/feedzilla_analyze.py
feedzilla/management/commands/feedzilla_refilter.py
feedzilla/management/commands/feedzilla_stats.py
feedzilla/management/commands/feedzilla_update.py
feedzilla/migrations/0001_initial.py
feedzilla/migrations/0002_auto__add_field_feed_created.py
feedzilla/migrations/0003_auto__add_field_feed_post_count__add_field_feed_active_post_count.py
feedzilla/migrations/0004_auto__chg_field_feed_feed_url__chg_field_feed_site_url__add_index_feed.py
feedzilla/migrations/0005_auto__add_index_feed_created.py
feedzilla/migrations/0006_auto__chg_field_post_tags.py
feedzilla/migrations/0007_auto__add_field_post_rawtags.py
feedzilla/migrations/0008_set_rawtags.py
feedzilla/migrations/0009_auto__del_field_post_tags.py
feedzilla/migrations/0010_auto__add_feedzillatag__add_feedzillatagitem.py
feedzilla/migrations/0011_setup_taggit_data.py
feedzilla/migrations/__init__.py
feedzilla/processors/__init__.py
feedzilla/processors/content_filter.py
feedzilla/static/feedzilla/css/custom.css
feedzilla/static/feedzilla/css/reset.css
feedzilla/static/feedzilla/css/style.css
feedzilla/static/feedzilla/img/add.png
feedzilla/static/feedzilla/img/border2.gif
feedzilla/static/feedzilla/img/external.png
feedzilla/static/feedzilla/img/feed-icon-big.png
