Metadata-Version: 1.1
Name: feedzilla
Version: 0.24
Summary: Django application for ATOM/RSS feeds aggregation i.e. planet engine
Home-page: http://bitbucket.org/lorien/feedzilla
Author: Gregory Petukhov
Author-email: lorien@lorien.name
License: BSD
Keywords: django application feeds syndication aggregation atom rss planet
Platform: UNKNOWN
Classifier: Development Status :: 4 - Beta
Classifier: Environment :: Web Environment
Classifier: Framework :: Django
Classifier: Intended Audience :: Developers
Classifier: License :: OSI Approved :: BSD License
Classifier: Operating System :: OS Independent
Classifier: Programming Language :: Python
Classifier: Topic :: Utilities
